pommes/__init__.py
pommes/common_plots.py
pommes/post_process.py
pommes/utils.py
pommes/examples/test_case/config.yaml
pommes/examples/test_case/data_source.yaml
pommes/examples/test_case/pre_process.yaml
pommes/examples/test_case/test.py
pommes/examples/test_case/data/availability.csv
pommes/examples/test_case/data/calendar.csv
pommes/examples/test_case/data/carbon.csv
pommes/examples/test_case/data/combined.csv
pommes/examples/test_case/data/combined_factor.csv
pommes/examples/test_case/data/combined_operation.csv
pommes/examples/test_case/data/conversion.csv
pommes/examples/test_case/data/conversion_factor.csv
pommes/examples/test_case/data/conversion_operation.csv
pommes/examples/test_case/data/demand.csv
pommes/examples/test_case/data/discount.csv
pommes/examples/test_case/data/eco.csv
pommes/examples/test_case/data/flexibility.csv
pommes/examples/test_case/data/import_hourly.csv
pommes/examples/test_case/data/import_yearly.csv
pommes/examples/test_case/data/load_shedding.csv
pommes/examples/test_case/data/spillage.csv
pommes/examples/test_case/data/storage.csv
pommes/examples/test_case/data/storage_factor.csv
pommes/examples/test_case/data/time_step_duration.csv
pommes/examples/test_case/data/transport.csv
pommes/examples/test_case/data/turpe.csv
pommes/examples/test_case/data/turpe_calendar.csv
pommes/examples/test_case/pre_process/pre_process.py
pommes/examples/test_case/pre_process/revert_pre_process.py
pommes/io/__init__.py
pommes/io/build_input_dataset.py
pommes/io/calculate_summaries.py
pommes/io/read_solution.py
pommes/io/save_solution.py
pommes/model/__init__.py
pommes/model/build_model.py
pommes/model/carbon.py
pommes/model/combined.py
pommes/model/conversion.py
pommes/model/flexible_demand.py
pommes/model/net_import.py
pommes/model/retrofit.py
pommes/model/storage.py
pommes/model/transport.py
pommes/model/turpe.py
pommes/model/data_validation/__init__.py
pommes/model/data_validation/dataset_check.py
pommes-0.3.2.dist-info/licenses/AUTHORS
pommes-0.3.2.dist-info/licenses/LICENCE.txt
pommes-0.3.2.dist-info/METADATA
pommes-0.3.2.dist-info/WHEEL
pommes-0.3.2.dist-info/top_level.txt
pommes-0.3.2.dist-info/RECORD
