Metadata-Version: 2.4
Name: pommes
Version: 0.3.2
Summary: Planning and Operation Model for Multi-Energy Systems
Author-email: Thibaut Knibiehly <thibaut.knibiehly@minesparis.psl.eu>, Hugo Hamburger <yassine.abdelouadoud@gmail.com>, Robin Girard <robin.girard@minesparis.psl.eu>, Yoann Chiche <yoann.chiche@minesparis.psl.eu>, Yassine Abdelouadoud <yassine.abdelouadoud@minesparis.psl.eu>
Maintainer-email: Thibaut Knibiehly <thibaut.knibiehly@minesparis.psl.eu>, Hugo Hamburger <yassine.abdelouadoud@gmail.com>, Robin Girard <robin.girard@minesparis.psl.eu>, Yoann Chiche <yoann.chiche@minesparis.psl.eu>, Yassine Abdelouadoud <yassine.abdelouadoud@minesparis.psl.eu>
License-Expression: MIT
Classifier: Development Status :: 3 - Alpha
Classifier: Operating System :: MacOS :: MacOS X
Classifier: Operating System :: Microsoft :: Windows
Classifier: Operating System :: POSIX :: Linux
Classifier: Programming Language :: Python :: 3.10
Classifier: Programming Language :: Python :: 3.11
Classifier: Programming Language :: Python :: 3.12
Classifier: Programming Language :: Python :: 3.13
Classifier: Topic :: Scientific/Engineering :: Physics
Requires-Python: <4.0.0,>=3.10
License-File: LICENCE.txt
License-File: AUTHORS
Requires-Dist: pandas
Requires-Dist: xarray
Requires-Dist: linopy
Requires-Dist: numpy
Requires-Dist: pyyaml
Requires-Dist: highspy
Requires-Dist: h5netcdf
Provides-Extra: notebooks
Requires-Dist: notebook; extra == "notebooks"
Requires-Dist: ipykernel; extra == "notebooks"
Requires-Dist: ipython; extra == "notebooks"
Requires-Dist: nbformat; extra == "notebooks"
Provides-Extra: visualisation
Requires-Dist: matplotlib; extra == "visualisation"
Provides-Extra: pre-process
Requires-Dist: pommes-pre-process; extra == "pre-process"
Provides-Extra: all
Requires-Dist: notebook; extra == "all"
Requires-Dist: ipykernel; extra == "all"
Requires-Dist: ipython; extra == "all"
Requires-Dist: nbformat; extra == "all"
Requires-Dist: matplotlib; extra == "all"
Requires-Dist: pommes-pre-process; extra == "all"
Dynamic: license-file
